django_channels_jwt/__init__.py
django_channels_jwt/middleware.py
django_channels_jwt/urls.py
django_channels_jwt/utils.py
django_channels_jwt/views.py
django_channels_jwt-0.0.3.dist-info/LICENSE
django_channels_jwt-0.0.3.dist-info/METADATA
django_channels_jwt-0.0.3.dist-info/WHEEL
django_channels_jwt-0.0.3.dist-info/top_level.txt
django_channels_jwt-0.0.3.dist-info/RECORD
