Metadata-Version: 2.1
Name: django-channels-jwt
Version: 0.0.3
Summary: Secure JWT Auth Middleware for Django Channels
Home-page: https://github.com/usamashehab/django-channels-jwt
Author: Usama Shehab
Author-email: usama.mh.shehab@gmail.com
License: MIT
Keywords: django,channels,jwt,auth,middleware,python,authentication
Platform: UNKNOWN
Classifier: Development Status :: 5 - Production/Stable
Classifier: Intended Audience :: Developers
Classifier: License :: OSI Approved :: MIT License
Classifier: Natural Language :: English
Classifier: Programming Language :: Python :: 3.11
Requires-Python: >=3.8
Requires-Dist: Django >=3.0.0
Requires-Dist: channels >=4.0.0
